lightsleep/__init__.py
lightsleep/exceptions.py
lightsleep/hook.py
lightsleep/idle.py
lightsleep/mtime.py
lightsleep/redis.py
lightsleep/sleep.py
lightsleep/websocket.py
lightsleep-0.0.6.data/scripts/lsleep.py
lightsleep-0.0.6.dist-info/LICENSE
lightsleep-0.0.6.dist-info/METADATA
lightsleep-0.0.6.dist-info/WHEEL
lightsleep-0.0.6.dist-info/top_level.txt
lightsleep-0.0.6.dist-info/RECORD
