Metadata-Version: 2.1
Name: lightsleep
Version: 0.0.6
Summary: sleep() you can interrupt with redis or websocket event
Home-page: https://github.com/yaroslaff/lightsleep
Author: Yaroslav Polyakov
Author-email: yaroslaff@gmail.com
License: MIT
Platform: UNKNOWN
Classifier: Development Status :: 3 - Alpha
Classifier: Intended Audience :: Developers
Classifier: License :: OSI Approved :: MIT License
Classifier: Programming Language :: Python :: 3.6
Requires-Python: >=3
Requires-Dist: python-socketio[client]
Requires-Dist: redis
Requires-Dist: setproctitle
